{
    "title": "Blueberry smoothie",
    "cookTime": "no cooking required",
    "prepTime": "less than 30 mins",
    "serves": "Serves 1",
    "recommendations": "2",
    "images": [
        
    ],
    "description": "",
    "author": {
        "michael_caines": "Michael Caines"
    },
    "show": {
        "b007yk5b": "Countryfile Summer Diaries"
    },
    "tips": [
        
    ],
    "flags": [
        "Vegetarian"
    ],
    "ingredients": {
        "default": [
            "175ml/6fl oz apple juice",
            "120ml/4fl oz natural yoghurt",
            "1 banana, peeled and roughly chopped",
            "170g/6oz blueberries (defrosted if frozen)"
        ]
    },
    "steps": [
        "Place all the ingredients into a blender and blend until smooth.",
        "To serve, pour into glasses."
    ],
    "howTos": [
        
    ],
    "videos": "[]"
}