{
    "author": {
        "ross_burden": "Ross Burden"
    },
    "cookTime": "10 to 30 mins",
    "description": "Not sure what to cook for yourself tonight? Treat yourself to this creamy fish bake, perfect with a chilled glass of white wine.",
    "dishes": [
        "oven-baked_dishes",
        "sauce",
        "stir-fries"
    ],
    "flags": [
        
    ],
    "howTos": [
        
    ],
    "images": [
        "http://ichef.bbci.co.uk/food/ic/food_16x9_608/recipes/broccoliandsalmonbak_77132_16x9.jpg"
    ],
    "ingredients": {
        "default": [
            "1 onion, chopped",
            "1 tsp olive oil",
            "20g/\u00beoz butter",
            "20g/\u00beoz plain flour",
            "150ml/5fl oz milk",
            "50g/1\u00beoz parmesan, grated",
            "150g/5\u00bcoz salmon steak",
            "150g/5\u00bcoz broccoli, cut into florets and steamed",
            "2 carrots, cut into batons and steamed",
            "6 cherry tomatoes"
        ]
    },
    "prepTime": "less than 30 mins",
    "recommendations": "5",
    "serves": "Serves 1",
    "show": {
        "b006vcgr": "Ready Steady Cook"
    },
    "steps": [
        "Preheat the oven to 220C/425F/Gas 7.",
        "Gently fry the onions in the oil in a saucepan and cook until soft. Stir in the butter and the flour. Mix thoroughly, cooking on a low heat for one minute.",
        "Pour in the milk, gradually, until everything is combined. Cook for two minutes.",
        "Add half the cheese to the sauce and reserve the other half.",
        "Meanwhile, pan-fry the salmon steak for one minute on each side.",
        "Lay the salmon steak in a small oven-proof dish.",
        "Add the broccoli, carrots and cherry tomatoes to the dish.",
        "Pour over the sauce and top with the rest of the cheese.",
        "Bake in the oven for ten minutes or until bubbling and golden."
    ],
    "tips": [
        
    ],
    "title": "Broccoli and salmon bake",
    "videos": "[]"
}