{
    "title": "Cranberry and pear sparkle",
    "cookTime": "no cooking required",
    "prepTime": "less than 30 mins",
    "serves": "Makes 2 litres/3\u00bd pints",
    "recommendations": "",
    "images": [
        
    ],
    "description": "",
    "author": {
        "the_vegetarian_society": "The Vegetarian Society"
    },
    "show": {
        
    },
    "tips": [
        
    ],
    "flags": [
        "Vegetarian"
    ],
    "ingredients": {
        "default": [
            "6 tbsp pear concentrate",
            "1 litre/1\u00be pint sparkling water",
            "1 litre/1\u00be pint cranberry juice",
            "1 medium pear, cut into 1cm/\u00bdin pieces",
            "sprigs of fresh mint"
        ]
    },
    "steps": [
        "Mix the pear concentrate with the sparkling water.",
        "Add the cranberry juice and chill well.",
        "Just before serving, add the chopped pear, and garnish with fresh mint leaves."
    ],
    "howTos": [
        
    ],
    "videos": "[]"
}