{
    "title": "Cr\u00eapes suzette",
    "cookTime": "less than 10 mins",
    "prepTime": "less than 30 mins",
    "serves": "Serves 1",
    "recommendations": "",
    "images": [
        
    ],
    "description": "",
    "author": {
        "brian_turner": "Brian Turner"
    },
    "show": {
        "b006vcgr": "Ready Steady Cook"
    },
    "tips": [
        
    ],
    "flags": [
        "Vegetarian"
    ],
    "ingredients": {
        "For the cr\u00eapes": [
            "150g/7oz plain flour",
            "2 free-range eggs",
            "75ml/2\u00bdfl oz whole milk",
            "75ml/2\u00bdfl oz double cream",
            "\u00bd clementine, juice only",
            "25g/1oz butter"
        ],
        "To serve": [
            "\u00bd clementine, chopped",
            "1 tbsp Greek yoghurt"
        ]
    },
    "steps": [
        "For the cr\u00eapes, place the flour, eggs, milk, double cream and clementine juice into a bowl and mix to make a smooth batter.",
        "Heat half of the butter in a non-stick frying pan, place a ladleful of batter into the pan, swirl around to coat the base of the pan and cook for one minute on each side, or until golden-brown. Remove from the pan and repeat with the remaining mixture to make a second pancake.",
        "To serve, place the pancakes onto a plate with the chopped clementine and a dollop of Greek yoghurt."
    ],
    "howTos": [
        
    ],
    "videos": "[]"
}