{
    "title": "Croissant 'bread and butter pudding'",
    "cookTime": "10 to 30 mins",
    "prepTime": "less than 30 mins",
    "serves": "Serves 2",
    "recommendations": "1",
    "images": [
        
    ],
    "description": "",
    "author": {
        "phil_vickery": "Phil Vickery"
    },
    "show": {
        "b006vcgr": "Ready Steady Cook"
    },
    "tips": [
        
    ],
    "flags": [
        "Vegetarian"
    ],
    "ingredients": {
        "default": [
            "200ml/7fl oz double cream",
            "100ml/3\u00bdoz whole milk",
            "1 tsp vanilla extract",
            "\u00bd orange, zest only",
            "1 free-range egg",
            "3 free-range egg yolks",
            "50g/1\u00bdoz caster sugar",
            "butter, for greasing",
            "1 ready-made croissant, cut into slices",
            "1 tbsp sultanas",
            "icing sugar, to dust"
        ]
    },
    "steps": [
        "Place the cream, milk, vanilla extract and orange zest into a saucepan and bring to a simmer.",
        "Place the egg, egg yolks and sugar into a large bowl and whisk together.",
        "Gradually pour the cream mixture onto the eggs, whisking continuously to make a smooth custard.",
        "Lightly grease a microwave-proof dish and place the croissant slices in the base of the dish. Sprinkle over the sultanas and pour over the custard mixture.",
        "Place in the microwave and cook on full power for four minutes, or until set.",
        "To serve, dust the pudding with icing sugar and caramelise with a mini-blowtorch. Place servings of the pudding into two bowls."
    ],
    "howTos": [
        "caramelising_sugar",
        "zesting_citrus_fruit"
    ],
    "videos": "[]"
}