{
    "author": {
        "phil_vickery": "Phil Vickery"
    },
    "cookTime": "10 to 30 mins",
    "cusine": "Portuguese",
    "description": "",
    "dishes": [
        "crepe",
        "custard",
        "oven-baked_dishes",
        "pastry"
    ],
    "flags": [
        "Vegetarian"
    ],
    "howTos": [
        
    ],
    "images": [
        
    ],
    "ingredients": {
        "default": [
            "3 sheets ready-made filo pastry",
            "butter, melted",
            "2 free-range eggs",
            "30ml/1\u00bcfl oz cream",
            "30ml/1\u00bcfl oz milk",
            "85g/3oz sugar",
            "vanilla essence, few drops"
        ]
    },
    "prepTime": "less than 30 mins",
    "recommendations": "",
    "serves": "Serves 1",
    "show": {
        "b006vcgr": "Ready Steady Cook"
    },
    "steps": [
        "Heat oven to 220C/425F/Gas 7.",
        "Line a crepe pan with filo pastry and butter the pastry. Add another sheet and so on to make a flan case.",
        "Mix the eggs, cream, milk, sugar and vanilla together and pour into the flan case.",
        "Bake in the oven for 5-8 minutes or until golden."
    ],
    "tips": [
        
    ],
    "title": "Fine egg custard flan",
    "videos": "[]"
}