{
    "author": {
        "garrey_dawson": "Garrey Dawson"
    },
    "cookTime": "10 to 30 mins",
    "description": "",
    "dishes": [
        "gratin",
        "oven-baked_dishes"
    ],
    "flags": [
        "Vegetarian"
    ],
    "howTos": [
        
    ],
    "images": [
        
    ],
    "ingredients": {
        "default": [
            "225g/8oz Brussels sprouts, trimmed",
            "2 tbsp olive oil",
            "2 sprigs fresh rosemary, chopped",
            "3 sprigs fresh thyme, chopped",
            "2 garlic cloves, roughly chopped"
        ]
    },
    "prepTime": "less than 30 mins",
    "recommendations": "",
    "serves": "Serves 2",
    "show": {
        "b006vcgr": "Ready Steady Cook"
    },
    "steps": [
        "Preheat the oven to 180C/350F/Gas 4.",
        "Boil the sprouts in salted water for about 3-4 minutes, then drain.",
        "Heat the oil in an ovenproof frying pan and fry the sprouts along with the herbs and garlic for 1-2 minutes. Transfer the pan to the oven and continue to cook for 10-12 minutes, or until the sprouts are tender.",
        "Serve in a gratin dish."
    ],
    "tips": [
        
    ],
    "title": "Herbed roasted sprouts",
    "videos": "[]"
}