{
    "author": {
        "james_tanner": "James Tanner"
    },
    "cookTime": "10 to 30 mins",
    "description": "",
    "dishes": [
        "jam"
    ],
    "flags": [
        "Vegetarian"
    ],
    "howTos": [
        "segmenting_citrus_fruit"
    ],
    "images": [
        
    ],
    "ingredients": {
        "default": [
            "75g/2\u00bd oz rice",
            "150ml/5fl oz milk",
            "1 orange, segmented, with juice and zest",
            "1 vanilla pod, seeds only",
            "50ml/1\u00befl oz double cream",
            "drizzle honey"
        ]
    },
    "prepTime": "less than 30 mins",
    "recommendations": "",
    "serves": "Serves 1",
    "show": {
        "b006vcgr": "Ready Steady Cook"
    },
    "steps": [
        "Place the rice, milk, orange juice, vanilla seeds, double cream and honey in a pan and bring to the boil.",
        "Turn down to a low heat and cook gently for 8-10 minutes or until the rice has absorbed all the liquid.",
        "Serve hot topped with the orange segments."
    ],
    "tips": [
        
    ],
    "title": "Honey, vanilla and orange rice pudding",
    "videos": "[]"
}