{
    "title": "Jersey Royal stack",
    "cookTime": "10 to 30 mins",
    "prepTime": "less than 30 mins",
    "serves": "Serves 2",
    "recommendations": "",
    "images": [
        
    ],
    "description": "",
    "author": {
        "mike_robinson": "Mike Robinson"
    },
    "show": {
        "b006v5y2": "Saturday Kitchen"
    },
    "tips": [
        
    ],
    "flags": [
        "Vegetarian"
    ],
    "ingredients": {
        "default": [
            "1 red onion, sliced",
            "10g/\u00bdoz capers",
            "250g/8\u00beoz Jersey potatoes, boiled till just tender",
            "100g/3\u00bdoz rocket",
            "3 plum tomatoes, sliced",
            "50g/1\u00beoz goats' cheese, crumbled",
            "butter",
            "olive oil",
            "salt and freshly ground black pepper"
        ]
    },
    "steps": [
        "Slice the onions and put into a pan on a very low heat with a small knob of butter and a drop of oil.",
        "Let the onions cook down for about 15 minutes. During this time, drain the capers and marinate them in olive oil and a little seasoning.",
        "Lightly smash potatoes with butter, salt, and pepper. Place in a ring, with rocket on top.",
        "Add three to four slices of tomato on top, then the cooked down red onion on top of that, then the capers, then the goats' cheese.",
        "Place under medium grill for two to three minutes.",
        "Serve with retained rocket and olive oil."
    ],
    "howTos": [
        
    ],
    "videos": "[]"
}