{
    "title": "Mary's classic Caesar salad",
    "cookTime": "less than 10 mins",
    "prepTime": "less than 30 mins",
    "serves": "Serves 4-6",
    "recommendations": "1",
    "images": [
        
    ],
    "description": "Making your own cro\u00fbtons is a great way of using up stale bread. They are perfect in this simple Caesar salad.",
    "author": {
        "mary_berry": "Mary Berry"
    },
    "show": {
        "b05vr6dl": "Mary Berry's Absolute Favourites"
    },
    "tips": [
        "The cro\u00fbtons can be made in advance and stored in an airtight container for 2 days. The dressing will keep for 2\u20133 days in a sealed container in the fridge."
    ],
    "flags": [
        
    ],
    "ingredients": {
        "default": [
            "3 tbsp olive oil",
            "2 slices of day-old white bread, crusts removed, cubed",
            "1 romaine lettuce heart, sliced",
            "30g/1oz Parmesan cheese, shaved",
            "salt and freshly ground black pepper"
        ],
        "For the dressing": [
            "6 tbsp light mayonnaise",
            "1\u00bd tbsp Dijon mustard",
            "2 tbsp grated Parmesan cheese",
            "\u00bd garlic clove, crushed",
            "a few drops of Worcestershire sauce"
        ]
    },
    "steps": [
        "Heat the olive oil in a non-stick frying pan, add the bread and fry over a high heat for 3\u20134 minutes until golden-brown. Remove with a slotted spoon, transfer to a bowl and season with salt and pepper.",
        "Put all the dressing ingredients in a bowl and beat together until smooth with 1\u20132 tablespoons water.",
        "Toss the romaine lettuce in the dressing and scatter with the toasted cro\u00fbtons and grated Parmesan."
    ],
    "howTos": [
        
    ],
    "videos": "[]"
}