{
    "title": "Onion rings",
    "cookTime": "10 to 30 mins",
    "prepTime": "less than 30 mins",
    "serves": "Serves 1",
    "recommendations": "3",
    "images": [
        
    ],
    "description": "",
    "author": {
        "nick_nairn": "Nick Nairn"
    },
    "show": {
        "b006vcgr": "Ready Steady Cook"
    },
    "tips": [
        
    ],
    "flags": [
        
    ],
    "ingredients": {
        "default": [
            "oil for deep frying",
            "\u00bd onion, sliced into rings",
            "50ml/1\u00befl oz milk",
            "100g/3\u00bdoz plain flour"
        ]
    },
    "steps": [
        "Heat the oil in a deep pan. (CAUTION: Hot oil can be very dangerous. Do not leave unattended.)",
        "Soak the onion rings in milk.",
        "Place the flour on the plate.",
        "Remove the onion rings from the milk and coat them in the flour.",
        "Deep fry in the oil for 2-3 minutes or until crisp and golden."
    ],
    "howTos": [
        
    ],
    "videos": "[]"
}