{
    "title": "Penne arrabiata with avocado and rocket salad",
    "cookTime": "10 to 30 mins",
    "prepTime": "less than 30 mins",
    "serves": "Serves 1",
    "recommendations": "",
    "images": [
        
    ],
    "description": "",
    "author": {
        "paul_rankin": "Paul Rankin"
    },
    "show": {
        "b006vcgr": "Ready Steady Cook"
    },
    "tips": [
        
    ],
    "flags": [
        "Vegetarian"
    ],
    "ingredients": {
        "For the pasta": [
            "125g/4\u00bdoz penne pasta, cooked according to packet instructions",
            "1 tbsp olive oil",
            "1 garlic clove, finely chopped",
            "\u00bc red onion, finely chopped",
            "\u00bd tsp dried chilli flakes",
            "1 tbsp tomato pur\u00e9e"
        ],
        "For the salad": [
            "\u00bd avocado, stone removed, sliced",
            "small handful rocket leaves",
            "1 tbsp olive oil",
            "\u00bd tbsp balsamic vinegar"
        ]
    },
    "steps": [
        "Place all the ingredients for the pasta into a serving bowl, mixing well to combine the ingredients.",
        "For the salad, place all the ingredients on a separate bowl, mixing together well. Serve alongside the bowl of pasta."
    ],
    "howTos": [
        
    ],
    "videos": "[]"
}