{
    "author": {
        "lesley_waters": "Lesley Waters"
    },
    "cookTime": "10 to 30 mins",
    "description": "",
    "dishes": [
        "stir-fries"
    ],
    "flags": [
        "Vegetarian"
    ],
    "howTos": [
        
    ],
    "images": [
        
    ],
    "ingredients": {
        "default": [
            "1 sweet potato, diced",
            "3 tbsp olive oil",
            "\u00bd red onion, chopped",
            "1 tsp ground coriander",
            "3 tbsp fresh coriander, chopped"
        ]
    },
    "prepTime": "less than 30 mins",
    "recommendations": "",
    "serves": "Serves 1",
    "show": {
        "b006vcgr": "Ready Steady Cook"
    },
    "steps": [
        "Cook the sweet potato in boiling water until just tender. Drain.",
        "In a pan heat the olive oil and add the red onions and ground coriander. Cook for 2-3 minutes.",
        "Add the sweet potatoes to the pan with the red onion, stir in the fresh coriander and cook until golden."
    ],
    "tips": [
        
    ],
    "title": "Saut\u00e9ed sweet potato with coriander",
    "videos": "[]"
}