{
    "author": {
        "nick_nairn": "Nick Nairn"
    },
    "cookTime": "no cooking required",
    "description": "",
    "dishes": [
        "salad"
    ],
    "flags": [
        "Vegetarian"
    ],
    "howTos": [
        
    ],
    "images": [
        
    ],
    "ingredients": {
        "default": [
            "1 chicory, shredded",
            "1 orange, peeled, segmented",
            "1 tbsp fresh chives, chopped",
            "handful each fresh chervil and parsley, chopped",
            "1 tbsp olive oil"
        ]
    },
    "prepTime": "less than 30 mins",
    "recommendations": "",
    "serves": "Serves 1",
    "show": {
        "b006vcgr": "Ready Steady Cook"
    },
    "steps": [
        "Place all the ingredients into a bowl and mix well.",
        "To serve, pile high on a large plate."
    ],
    "tips": [
        
    ],
    "title": "Salad of chicory and orange segments",
    "videos": "[]"
}