{
    "author": {
        "paul_rankin": "Paul Rankin"
    },
    "cookTime": "10 to 30 mins",
    "description": "",
    "dishes": [
        "icing",
        "pie",
        "prepare-ahead_desserts",
        "salad",
        "salsa"
    ],
    "flags": [
        
    ],
    "howTos": [
        
    ],
    "images": [
        
    ],
    "ingredients": {
        "For the chilli oil": [
            "50ml/2fl oz olive oil",
            "2 fresh chillies, chopped, with seeds removed"
        ],
        "For the salsa": [
            "75g/2\u00beoz pineapple, cut into chunky pieces",
            "1 lemon, juice only",
            "1 lime, juice only",
            "1 tbsp of icing sugar",
            "15g/\u00bd oz Drunken Lady lettuce, to serve (substitute mixed salad leaves or seasonal leaves)",
            "15g/\u00bd oz Lazy Blonde lettuce, to serve (substitute mixed salad leaves or seasonal leaves)"
        ],
        "For the squid": [
            "1 tube squid, cleaned and scored",
            "2 tbsp cornflour",
            "5 tbsp plain flour",
            "1 free-range egg white",
            "300ml/10\u00bdfl oz hot oil for frying"
        ]
    },
    "prepTime": "less than 30 mins",
    "recommendations": "",
    "serves": "Serves 1",
    "show": {
        "b006vcgr": "Ready Steady Cook"
    },
    "steps": [
        "To prepare the squid, cut it into medium-sized strips.",
        "Make batter by mixing the cornflour, plain flour and egg white to form a smooth paste.",
        "Dip the squid into the mixture and deep-fry for 1-2 minutes. (CAUTION: Hot oil can be very dangerous. Do not leave unattended.)",
        "Drain on kitchen paper.",
        "To make the chilli oil, warm in a small pan the oil and the chilli for two minutes and remove from the heat.",
        "To prepare the salsa, in a medium sized bowl combine the chilli, pineapple, lemon and lime juices and the icing sugar",
        "Serve the chilli squid with salsa on the side and with the chilli oil over the squid, on top of the lettuce leaves."
    ],
    "tips": [
        
    ],
    "title": "Salt chilli squid with salsa",
    "videos": "[]"
}