{
    "author": {
        "simon_rimmer": "Simon Rimmer"
    },
    "cookTime": "30 mins to 1 hour",
    "cusine": "British",
    "description": "",
    "dishes": [
        "custard",
        "pie",
        "stir-fries"
    ],
    "flags": [
        "Vegetarian"
    ],
    "howTos": [
        "zesting_citrus_fruit"
    ],
    "images": [
        
    ],
    "ingredients": {
        "default": [
            "300g/10\u00bdoz plain flour",
            "2 tsp baking powder",
            "150g/5\u00bcoz shredded suet (vegetarians can use vegetable suet)",
            "75g/2\u00bdoz sugar",
            "100g/3\u00bdoz currants",
            "1 orange, zest only",
            "2 bananas, peeled and chopped",
            "150ml/5\u00bcfl oz whole milk",
            "butter, for greasing",
            "custard, to serve"
        ]
    },
    "prepTime": "less than 30 mins",
    "recommendations": "1",
    "serves": "Serves 4-6",
    "show": {
        "b006v85g": "Something for the Weekend"
    },
    "steps": [
        "In a large bowl, mix together the flour, baking powder, suet, sugar, currants and orange zest.",
        "Stir in the banana pieces and gradually pour in the milk to make a dough.",
        "Roll the dough into a cylinder about 15cm x 5cm/6in x 2in. Wrap loosely in buttered greaseproof paper, leaving room for it to rise, and seal at each end.",
        "Place the pudding into a steamer, cover and steam for an hour.",
        "To serve, remove the pudding from the steamer and cut into slices. Place into serving bowls and pour over some custard."
    ],
    "tips": [
        
    ],
    "title": "Spotted dick with banana",
    "videos": "[]"
}