{
    "title": "Steamed mackerel with poached leeks in red wine",
    "cookTime": "10 to 30 mins",
    "prepTime": "less than 30 mins",
    "serves": "Serves 1",
    "recommendations": "",
    "images": [
        
    ],
    "description": "",
    "author": {
        "james_tanner": "James Tanner"
    },
    "show": {
        "b006vcgr": "Ready Steady Cook"
    },
    "tips": [
        
    ],
    "flags": [
        
    ],
    "ingredients": {
        "default": [
            "1 mackerel, cut into fillets",
            "\u00bd lemon, cut into slices",
            "salt and freshly ground black pepper"
        ],
        "For the leeks": [
            "150ml/5fl oz red wine",
            "150g/5\u00bcoz leeks, sliced"
        ]
    },
    "steps": [
        "Bring a pan of water to the simmer and place a bamboo steamer on top.",
        "Arrange the lemon slices in the steamer and place the mackerel fillets inside. Season with salt and freshly ground black pepper. Steam for 3-4 minutes, or until cooked.",
        "For the leeks, heat the red wine in a pan. Add the leeks. Poach for 4-5 minutes, until tender.",
        "To serve, place the mackerel fillets on a serving plate and spoon the poached leeks alongside."
    ],
    "howTos": [
        
    ],
    "videos": "[]"
}