{
    "author": {
        "garrey_dawson": "Garrey Dawson"
    },
    "cookTime": "no cooking required",
    "description": "",
    "dishes": [
        "salad",
        "stir-fries"
    ],
    "flags": [
        "Vegetarian"
    ],
    "howTos": [
        
    ],
    "images": [
        
    ],
    "ingredients": {
        "default": [
            "5 tbsp olive oil",
            "2 tbsp white wine vinegar",
            "1 tbsp Dijon mustard",
            "salt and freshly ground black pepper",
            "2 tbsp chopped fresh chives",
            "200g/7oz new potatoes, cooked and halved, still warm"
        ]
    },
    "prepTime": "less than 30 mins",
    "recommendations": "",
    "serves": "Serves 2",
    "show": {
        "b006vcgr": "Ready Steady Cook"
    },
    "steps": [
        "In a bowl, whisk together the oil, vinegar and Dijon mustard. Season with salt and freshly ground black pepper, to taste, and stir in the chives.",
        "Stir the warm cooked new potatoes into the dressing and serve warm."
    ],
    "tips": [
        
    ],
    "title": "Warm potato salad with herb dressing",
    "videos": "[]"
}